{
    "title": "Minestra ai tre pomodori",
    "ingredients": [
        {
            "ingredient": "Chicchi di farina di legumi (lenticchie rosse e piselli)",
            "quantity": "300 g"
        },
        {
            "ingredient": "Pomodorini gialli",
            "quantity": "120 g"
        },
        {
            "ingredient": "Pomodori sardi (camone)",
            "quantity": "verdi 100 g"
        },
        {
            "ingredient": "Pomodori pizzutelli",
            "quantity": "240 g"
        },
        {
            "ingredient": "Basilico",
            "quantity": "10 g"
        },
        {
            "ingredient": "Spinacini",
            "quantity": "20 g"
        },
        {
            "ingredient": "Scalogno",
            "quantity": "1"
        },
        {
            "ingredient": "Olio extravergine d'oliva",
            "quantity": "q.b."
        },
        {
            "ingredient": "Sale fino",
            "quantity": "q.b."
        },
        {
            "ingredient": "Pepe nero",
            "quantity": "q.b."
        }
    ],
    "preparation": " Per preparareÂ la minestra ai tre pomodori, iniziate a mondare e affettare lo scalogno 1, poi lavate e riducete a spicchi i pomodori camone, a metÃ i pomodorini pizzutelli e i pomodorini gialli 2. In una casseruola versate un giro di olio e unite lo scalogno 3; fate soffriggere mescolando di tanto in tanto. Aggiungete poi i pomodori 4, mescolate e unite anche le foglie di basilico e lo spinacino 5. Fate cuocere il tutto a fiamma bassa per 10 minuti 6, mescolando di tanto in tanto. Versate direttamente nel tegame i chicchi di farina di legumi 7, mescolate 8 e unite lâacqua 9, regolate di sale e pepe 10 e portate a cottura per circa 7 minuti. Dovrete ottenere un composto piuttosto cremoso 11. ImpiattateÂ la vostra minestraÂ ai tre pomodori, aggiungendo a piacere altre foglie di basilico fresco o spinacino 12. "
}