{
    "title": "Risotto pannerone e pere",
    "ingredients": [
        {
            "ingredient": "Riso Carnaroli",
            "quantity": "350 g"
        },
        {
            "ingredient": "Pere Decana",
            "quantity": "(oppure altra qualitÃ succosa) non trattate 200 g"
        },
        {
            "ingredient": "Pannerone",
            "quantity": "200 g"
        },
        {
            "ingredient": "Vino bianco",
            "quantity": "50 g"
        },
        {
            "ingredient": "Cipolle bianche",
            "quantity": "50 g"
        },
        {
            "ingredient": "Olio di oliva",
            "quantity": "extravergine 30 g"
        },
        {
            "ingredient": "Burro",
            "quantity": "20 g"
        },
        {
            "ingredient": "Brodo vegetale",
            "quantity": "800 g"
        }
    ],
    "preparation": " Per preparare il risotto pannerone e pere iniziate a preparare il brodo vegetale. Una volta pronto, tritate finemente la cipolla 1, versate sia il burro che l’olio in un tegame 2, scaldatelo e unite la cipolla 3. Aggiungete un mestolo di brodo caldo 4 e lasciate appassire il soffritto; quindi unite il riso 5 e tostatelo mescolando spesso. Solo quando questo avrà cambiato colore potrete sfumare con il vino bianco 6. Continuate la cottura del riso aggiungendo un mestolo di brodo di tanto in tanto 7 e mescolandolo frequentemente. Nel frattempo tagliate il pannerone: prima a listarelle 8 e poi a cubetti 9. Lavate le pere, dividetele in 4 ed eliminate il torsolo centrale con un coltellino senza eliminare la buccia 10, quindi tagliate ogni spicchio a cubetti 11. Quando il riso sarà quasi cotto unite la dadolata di pere 12 e i cubetti di pannerone 13. Amalgamate bene il tutto 14 e servite il vostro risotto pannerone e pere 15. "
}